LICENSE
README.md
pyproject.toml
src/recipe_extractor_tools/__init__.py
src/recipe_extractor_tools/database_service.py
src/recipe_extractor_tools/database_tables.py
src/recipe_extractor_tools/details.py
src/recipe_extractor_tools/encoder.py
src/recipe_extractor_tools/listings.py
src/recipe_extractor_tools/logger_service.py
src/recipe_extractor_tools/modes.py
src/recipe_extractor_tools/scaper_service.py
src/recipe_extractor_tools.egg-info/PKG-INFO
src/recipe_extractor_tools.egg-info/SOURCES.txt
src/recipe_extractor_tools.egg-info/dependency_links.txt
src/recipe_extractor_tools.egg-info/requires.txt
src/recipe_extractor_tools.egg-info/top_level.txt