Metadata-Version: 2.2
Name: recipe_extractor_tools
Version: 0.0.2
Summary: Models and tools for a recipe extractors
Author-email: Sebastien Hamel <sebhamel09@gmail.com>
Project-URL: Documentation, https://recipe-extractor-tools.readthedocs.io/en/latest/
Project-URL: Homepage, https://github.com/sebastienhamel/basic_recipe_extrator_tools
Project-URL: Repository, https://github.com/sebastienhamel/basic_recipe_extrator_tools
Project-URL: Issuses, https://github.com/sebastienhamel/basic_recipe_extrator_tools/issues
Keywords: recipe,models,ingredients,methods
Classifier: Programming Language :: Python :: 3
Classifier: Operating System :: OS Independent
Classifier: License :: OSI Approved :: MIT License
Requires-Python: >3.10
License-File: LICENSE
Requires-Dist: pydantic
Requires-Dist: sqlalchemy
Requires-Dist: loguru
Requires-Dist: mysql-connector-python
